timeN.py
timeN-1.4.dist-info/LICENSE.txt
timeN-1.4.dist-info/METADATA
timeN-1.4.dist-info/WHEEL
timeN-1.4.dist-info/top_level.txt
timeN-1.4.dist-info/RECORD
